freedom/application/application.py
freedom/application/command_bus.py
freedom/application/dto.py
freedom/application/event_emitter.py
freedom/application/event_stream.py
freedom/application/inflector.py
freedom/application/mapper.py
freedom/application/middleware.py
freedom/application/provider.py
freedom/domain/aggregate.py
freedom/domain/business_rule.py
freedom/domain/command.py
freedom/domain/command_handler.py
freedom/domain/entity.py
freedom/domain/entity_id.py
freedom/domain/event.py
freedom/domain/event_handler.py
freedom/domain/repository.py
freedom/domain/valueobject.py
freedom/infrastructure/command_bus.py
freedom/infrastructure/entity_id.py
freedom/infrastructure/event_emitter.py
freedom/infrastructure/event_stream.py
freedom/infrastructure/inflector.py
freedom/infrastructure/middleware.py
freedom/infrastructure/provider.py
freedom/infrastructure/repository.py
freedom/py.typed
freedom/sentinel.py
freedom/type_hints.py
freedom/util.py
freedddom-1.0.2a0.dist-info/LICENSE
freedddom-1.0.2a0.dist-info/METADATA
freedddom-1.0.2a0.dist-info/WHEEL
freedddom-1.0.2a0.dist-info/RECORD
